llama_index/agent/introspective/__init__.py
llama_index/agent/introspective/step.py
llama_index/agent/introspective/reflective/__init__.py
llama_index/agent/introspective/reflective/self_reflection.py
llama_index/agent/introspective/reflective/tool_interactive_reflection.py
llama_index_agent_introspective-0.3.2.dist-info/METADATA
llama_index_agent_introspective-0.3.2.dist-info/WHEEL
llama_index_agent_introspective-0.3.2.dist-info/licenses/LICENSE
llama_index_agent_introspective-0.3.2.dist-info/RECORD
