Metadata-Version: 2.4
Name: llama-index-agent-introspective
Version: 0.3.2
Summary: llama-index agent introspective integration
Author-email: Andrei Fajardo <andrei@runllama.ai>, Jerry Liu <jerry@runllama.ai>
Maintainer: jerryjliu
License-Expression: MIT
License-File: LICENSE
Requires-Python: <4.0,>=3.9
Requires-Dist: llama-index-core<0.13,>=0.12.0
